AutoCom.py
__init__.py
cli.py
version.py
autocom-1.0.5.dist-info/licenses/LICENSE
components/CommandDeviceDict.py
components/CommandExecutor.py
components/DataStore.py
components/Device.py
components/__init__.py
utils/ActionHandler.py
utils/CustomActionHandler.py
utils/__init__.py
utils/common.py
utils/datastore_manager.py
autocom-1.0.5.dist-info/METADATA
autocom-1.0.5.dist-info/WHEEL
autocom-1.0.5.dist-info/entry_points.txt
autocom-1.0.5.dist-info/top_level.txt
autocom-1.0.5.dist-info/RECORD
