Metadata-Version: 2.4
Name: autocom
Version: 1.0.5
Summary: 一款用于自动化执行串口指令的脚本，支持多设备、多指令的串行和并行执行
Home-page: https://github.com/iFishin/AutoCom
Author: iFishin
Author-email: iFishin <your.email@example.com>
License: MIT
Project-URL: Homepage, https://github.com/iFishin/AutoCom
Project-URL: Bug Reports, https://github.com/iFishin/AutoCom/issues
Project-URL: Source, https://github.com/iFishin/AutoCom
Keywords: serial,automation,testing,embedded,iot
Classifier: Development Status :: 4 - Beta
Classifier: Intended Audience :: Developers
Classifier: Topic :: Software Development :: Testing
Classifier: License :: OSI Approved :: MIT License
Classifier: Programming Language :: Python :: 3
Classifier: Programming Language :: Python :: 3.7
Classifier: Programming Language :: Python :: 3.8
Classifier: Programming Language :: Python :: 3.9
Classifier: Programming Language :: Python :: 3.10
Classifier: Programming Language :: Python :: 3.11
Classifier: Operating System :: OS Independent
Requires-Python: >=3.7
License-File: LICENSE
Requires-Dist: pyserial>=3.5
Dynamic: author
Dynamic: home-page
Dynamic: license-file
Dynamic: requires-python
